[{
        "cityName": "Phnom Penh",
        "cityCountry": "Phnom Penh, Cambodia"
    },
    {
        "cityName": "Banteay Meanchey",
        "cityCountry": "Banteay Meanchey, Cambodia"
    },
    {
        "cityName": "Battambang",
        "cityCountry": "Battambang, Cambodia"
    },
    {
        "cityName": "Kampong Cham",
        "cityCountry": "Kampong Cham, Cambodia"
    },
    {
        "cityName": "Kampong Speu",
        "cityCountry": "Kampong Speu, Cambodia"
    },
    {
        "cityName": "Kampot",
        "cityCountry": "Kampot, Cambodia"
    },
    {
        "cityName": "Kandal",
        "cityCountry": "Kandal, Cambodia"
    },
    {
        "cityName": "Kep",
        "cityCountry": "Kep, Cambodia"
    },
    {
        "cityName": "Koh Kong",
        "cityCountry": "Koh Kong, Cambodia"
    },
    {
        "cityName": "Kratie",
        "cityCountry": "Kratie, Cambodia"
    },
    {
        "cityName": "Mondulkiri",
        "cityCountry": "Mondulkiri, Cambodia"
    },
    {
        "cityName": "Oddor Meanchey",
        "cityCountry": "Oddor Meanchey, Cambodia"
    },
    {
        "cityName": "Pailin",
        "cityCountry": "Pailin, Cambodia"
    },
    {
        "cityName": "Prey Veng",
        "cityCountry": "Prey Veng, Cambodia"
    },
    {
        "cityName": "Pursat",
        "cityCountry": "Pursat, Cambodia"
    },
    {
        "cityName": "Rattanakiri",
        "cityCountry": "Rattanakiri, Cambodia"
    },
    {
        "cityName": "Siem Reap",
        "cityCountry": "Siem Reap, Cambodia"
    },
    {
        "cityName": "Sihanouk ville",
        "cityCountry": "Sihanouk ville, Cambodia"
    },
    {
        "cityName": "Stung Treng",
        "cityCountry": "Stung Treng, Cambodia"
    },
    {
        "cityName": "Svay Rieng",
        "cityCountry": "Svay Rieng, Cambodia"
    },
    {
        "cityName": "Takeo",
        "cityCountry": "Takeo, Cambodia"
    },
    {
        "cityName": "Kampong Thom",
        "cityCountry": "Kampong Thom, Cambodia"
    },
    {
        "cityName": "Preah Vihear",
        "cityCountry": "Preah Vihear, Cambodia"
    },
    {
        "cityName": "Tbong Khmum",
        "cityCountry": "Tbong Khmum, Cambodia"
    }
]